odoo10_addon_stock_pack_operation_auto_fill-10.0.1.0.1-py2.7-nspkg.pth
odoo/addons/stock_pack_operation_auto_fill/README.rst
odoo/addons/stock_pack_operation_auto_fill/__init__.py
odoo/addons/stock_pack_operation_auto_fill/__manifest__.py
odoo/addons/stock_pack_operation_auto_fill/models/__init__.py
odoo/addons/stock_pack_operation_auto_fill/models/stock_picking.py
odoo/addons/stock_pack_operation_auto_fill/static/description/icon.png
odoo/addons/stock_pack_operation_auto_fill/tests/__init__.py
odoo/addons/stock_pack_operation_auto_fill/tests/test_stock_picking.py
odoo/addons/stock_pack_operation_auto_fill/views/stock_picking.xml
odoo10_addon_stock_pack_operation_auto_fill-10.0.1.0.1.dist-info/DESCRIPTION.rst
odoo10_addon_stock_pack_operation_auto_fill-10.0.1.0.1.dist-info/METADATA
odoo10_addon_stock_pack_operation_auto_fill-10.0.1.0.1.dist-info/RECORD
odoo10_addon_stock_pack_operation_auto_fill-10.0.1.0.1.dist-info/WHEEL
odoo10_addon_stock_pack_operation_auto_fill-10.0.1.0.1.dist-info/metadata.json
odoo10_addon_stock_pack_operation_auto_fill-10.0.1.0.1.dist-info/namespace_packages.txt
odoo10_addon_stock_pack_operation_auto_fill-10.0.1.0.1.dist-info/top_level.txt
